astroparse/__init__.py
astroparse/defaults.py
astroparse/parse.py
astroparse/reader.py
astroparse-0.1.3.dist-info/licenses/LICENSE
astroparse-0.1.3.dist-info/METADATA
astroparse-0.1.3.dist-info/WHEEL
astroparse-0.1.3.dist-info/top_level.txt
astroparse-0.1.3.dist-info/RECORD
