Metadata-Version: 2.4
Name: astroparse
Version: 0.1.3
Summary: Flexible parsing utility for irregular text data tables.
Author-email: Anthony Atkinson <asa15@rice.edu>
License-Expression: GPL-3.0-only
Project-URL: Homepage, https://github.com/asatk/astroparse
Project-URL: Issues, https://github.com/asatk/astroparse/issues
Classifier: Programming Language :: Python :: 3
Classifier: Operating System :: OS Independent
Requires-Python: >=3.10
License-File: LICENSE
Requires-Dist: astropy
Dynamic: license-file
